scplode/__init__.py
scplode/scplode.py
scplode-0.1.0.dist-info/METADATA
scplode-0.1.0.dist-info/WHEEL
scplode-0.1.0.dist-info/top_level.txt
scplode-0.1.0.dist-info/RECORD
