Metadata-Version: 2.4
Name: scplode
Version: 0.1.0
Summary: scplode: a memory-efficient fast accesser for adata files
Author-email: Ryosuke Kita <rkita4@gmail.com>
Project-URL: Homepage, https://github.com/rkita4/scplode
Project-URL: Issues, https://github.com/rkita4/scplode/issues
Classifier: Development Status :: 3 - Alpha
Classifier: Intended Audience :: Developers
Classifier: License :: OSI Approved :: MIT License
Classifier: Programming Language :: Python :: 3
Classifier: Programming Language :: Python :: 3.7
Classifier: Programming Language :: Python :: 3.8
Classifier: Programming Language :: Python :: 3.9
Classifier: Programming Language :: Python :: 3.10
Classifier: Programming Language :: Python :: 3.11
Classifier: Programming Language :: Python :: 3.12
Requires-Python: >=3.7
Requires-Dist: pandas
Requires-Dist: numpy
Requires-Dist: anndata
